chemchef/__init__.py
chemchef/agent/__init__.py
chemchef/agent/agent.py
chemchef/agent/agent_responses.py
chemchef/agent/example_end_to_end.py
chemchef/agent/test_LLM_agent.py
chemchef/agent/tools.py
chemchef/agent/search_critique/__init__.py
chemchef/agent/search_critique/search_critique.py
chemchef/agent/search_critique/test_LLM_search_critique.py
chemchef/agent/summarization/__init__.py
chemchef/agent/summarization/chunking.py
chemchef/agent/summarization/summarization.py
chemchef/agent/summarization/test_LLM_summarization.py
chemchef/agent/summarization/test_chunking.py
chemchef/clients/__init__.py
chemchef/clients/chroma/__init__.py
chemchef/clients/chroma/chroma_client.py
chemchef/clients/chroma/test_chroma_client.py
chemchef/clients/internet/__init__.py
chemchef/clients/internet/download.py
chemchef/clients/internet/google.py
chemchef/clients/internet/test_download.py
chemchef/clients/internet/test_google.py
chemchef/clients/openai/__init__.py
chemchef/clients/openai/chatgpt_client.py
chemchef/clients/openai/embeddings_client.py
chemchef/clients/openai/test_LLM_chatgpt_client.py
chemchef/clients/openai/test_LLM_embeddings_client.py
chemchef/clients/openai/test_LLM_embeddings_client_examples.py
chemchef/engine/__init__.py
chemchef/engine/document_table.py
chemchef/engine/example_end_to_end.py
chemchef/engine/test_document_table.py
chemchef/engine/extraction/__init__.py
chemchef/engine/extraction/extraction.py
chemchef/engine/extraction/schemas.py
chemchef/engine/extraction/test_LLM_extraction_examples.py
chemchef/engine/extraction/test_extraction.py
chemchef/engine/generation/__init__.py
chemchef/engine/generation/generation.py
chemchef/engine/generation/test_LLM_generation_examples.py
chemchef/engine/generation/test_generation.py
chemchef/engine/indexing/__init__.py
chemchef/engine/indexing/fuzzy_index.py
chemchef/engine/indexing/keyword_similarity.py
chemchef/engine/indexing/query_expressions.py
qbchemchef-0.0.13.dist-info/METADATA
qbchemchef-0.0.13.dist-info/WHEEL
qbchemchef-0.0.13.dist-info/top_level.txt
qbchemchef-0.0.13.dist-info/RECORD
