Metadata-Version: 2.1
Name: qbchemchef
Version: 0.0.13
Summary: LLM-based tools for information retrieval
Author: Kenny Wong
Author-email: kenny@quantumboost.com
Requires-Python: >3.9.0
Requires-Dist: aiohttp ==3.8.5
Requires-Dist: aiosignal ==1.3.1
Requires-Dist: annotated-types ==0.5.0
Requires-Dist: anyio ==3.7.1
Requires-Dist: async-timeout ==4.0.3
Requires-Dist: attrs ==23.1.0
Requires-Dist: backoff ==2.2.1
Requires-Dist: beautifulsoup4 ==4.12.2
Requires-Dist: bleach ==6.0.0
Requires-Dist: certifi ==2023.7.22
Requires-Dist: cffi ==1.15.1
Requires-Dist: charset-normalizer ==3.2.0
Requires-Dist: chroma-hnswlib ==0.7.2
Requires-Dist: chromadb ==0.4.6
Requires-Dist: click ==8.1.7
Requires-Dist: coloredlogs ==15.0.1
Requires-Dist: cryptography ==41.0.3
Requires-Dist: docutils ==0.20.1
Requires-Dist: et-xmlfile ==1.1.0
Requires-Dist: fastapi ==0.99.1
Requires-Dist: flatbuffers ==23.5.26
Requires-Dist: frozenlist ==1.4.0
Requires-Dist: googlesearch-python ==1.2.3
Requires-Dist: h11 ==0.14.0
Requires-Dist: html2text ==2020.1.16
Requires-Dist: httptools ==0.6.0
Requires-Dist: humanfriendly ==10.0
Requires-Dist: idna ==3.4
Requires-Dist: importlib-metadata ==6.8.0
Requires-Dist: importlib-resources ==6.0.1
Requires-Dist: iniconfig ==2.0.0
Requires-Dist: jaraco.classes ==3.3.0
Requires-Dist: jeepney ==0.8.0
Requires-Dist: keyring ==24.2.0
Requires-Dist: markdown-it-py ==3.0.0
Requires-Dist: mdurl ==0.1.2
Requires-Dist: monotonic ==1.6
Requires-Dist: more-itertools ==10.1.0
Requires-Dist: mpmath ==1.3.0
Requires-Dist: multidict ==6.0.4
Requires-Dist: mypy ==1.5.1
Requires-Dist: mypy-extensions ==1.0.0
Requires-Dist: numpy ==1.25.2
Requires-Dist: onnxruntime ==1.15.1
Requires-Dist: openai ==0.27.8
Requires-Dist: openpyxl ==3.1.2
Requires-Dist: overrides ==7.4.0
Requires-Dist: packaging ==23.1
Requires-Dist: pandas ==2.0.3
Requires-Dist: pandas-stubs ==2.0.3.230814
Requires-Dist: pkginfo ==1.9.6
Requires-Dist: pluggy ==1.2.0
Requires-Dist: posthog ==3.0.2
Requires-Dist: protobuf ==4.24.1
Requires-Dist: pulsar-client ==3.2.0
Requires-Dist: pycparser ==2.21
Requires-Dist: pydantic ==1.10.12
Requires-Dist: pydantic-core ==2.6.1
Requires-Dist: Pygments ==2.16.1
Requires-Dist: PyPDF2 ==3.0.1
Requires-Dist: PyPika ==0.48.9
Requires-Dist: pytest ==7.4.0
Requires-Dist: pytest-rerunfailures ==12.0
Requires-Dist: python-dateutil ==2.8.2
Requires-Dist: python-dotenv ==1.0.0
Requires-Dist: pytz ==2023.3
Requires-Dist: PyYAML ==6.0.1
Requires-Dist: readme-renderer ==41.0
Requires-Dist: requests ==2.31.0
Requires-Dist: requests-toolbelt ==1.0.0
Requires-Dist: rfc3986 ==2.0.0
Requires-Dist: rich ==13.5.2
Requires-Dist: SecretStorage ==3.3.3
Requires-Dist: six ==1.16.0
Requires-Dist: sniffio ==1.3.0
Requires-Dist: soupsieve ==2.4.1
Requires-Dist: starlette ==0.27.0
Requires-Dist: sympy ==1.12
Requires-Dist: tokenizers ==0.13.3
Requires-Dist: tqdm ==4.66.1
Requires-Dist: twine ==4.0.2
Requires-Dist: types-pytz ==2023.3.0.1
Requires-Dist: types-requests ==2.31.0.2
Requires-Dist: types-urllib3 ==1.26.25.14
Requires-Dist: typing-extensions ==4.7.1
Requires-Dist: tzdata ==2023.3
Requires-Dist: urllib3 ==2.0.4
Requires-Dist: uvicorn ==0.23.2
Requires-Dist: uvloop ==0.17.0
Requires-Dist: watchfiles ==0.19.0
Requires-Dist: webencodings ==0.5.1
Requires-Dist: websockets ==11.0.3
Requires-Dist: yarl ==1.9.2
Requires-Dist: zipp ==3.16.2
